wbia_orientation/__init__.py
wbia_orientation/__main__.py
wbia_orientation/_plugin.py
wbia_orientation/_version.py
wbia_orientation/test.py
wbia_orientation/train.py
wbia_orientation/models/__init__.py
wbia_orientation/models/cls_hrnet.py
wbia_orientation/models/orientation_net.py
wbia_orientation-4.0.1.dist-info/LICENSE
wbia_orientation-4.0.1.dist-info/METADATA
wbia_orientation-4.0.1.dist-info/WHEEL
wbia_orientation-4.0.1.dist-info/top_level.txt
wbia_orientation-4.0.1.dist-info/RECORD
