Metadata-Version: 2.1
Name: wbia-orientation
Version: 4.0.1
Summary: wbia_orientation - A plug-in for detecting the orientation of various species in images for WBIA system
Home-page: https://github.com/WildbookOrg/wbia-plugin-orientation
Author: Olga Moskvyak, Jason Parham
Author-email: olgamoskvyak@gmail.com
License: Apache Version 2.0
Platform: UNKNOWN
Classifier: Development Status :: 6 - Mature
Classifier: License :: OSI Approved :: BSD License
Classifier: Intended Audience :: Developers
Classifier: Intended Audience :: Science/Research
Classifier: Operating System :: MacOS :: MacOS X
Classifier: Operating System :: Unix
Classifier: Topic :: Software Development :: Libraries :: Python Modules
Classifier: Topic :: Utilities
Classifier: Programming Language :: Python :: 3
Classifier: Programming Language :: Python :: 3.5
Classifier: Programming Language :: Python :: 3.6
Classifier: Programming Language :: Python :: 3.7
Classifier: Programming Language :: Python :: 3.8
License-File: LICENSE
Requires-Dist: efficientnet-pytorch
Requires-Dist: matplotlib
Requires-Dist: numpy
Requires-Dist: scikit-image
Requires-Dist: tensorboardX
Requires-Dist: torch
Requires-Dist: torchvision
Requires-Dist: tqdm
Requires-Dist: wbia-utool
Requires-Dist: wildbook-ia
Requires-Dist: yacs
Provides-Extra: all
Requires-Dist: cmake ; extra == 'all'
Requires-Dist: ninja ; extra == 'all'
Requires-Dist: scikit-build ; extra == 'all'
Requires-Dist: setuptools ; extra == 'all'
Requires-Dist: setuptools-scm[toml] ; extra == 'all'
Requires-Dist: wheel ; extra == 'all'
Requires-Dist: efficientnet-pytorch ; extra == 'all'
Requires-Dist: matplotlib ; extra == 'all'
Requires-Dist: numpy ; extra == 'all'
Requires-Dist: scikit-image ; extra == 'all'
Requires-Dist: tensorboardX ; extra == 'all'
Requires-Dist: torch ; extra == 'all'
Requires-Dist: torchvision ; extra == 'all'
Requires-Dist: tqdm ; extra == 'all'
Requires-Dist: wbia-utool ; extra == 'all'
Requires-Dist: wildbook-ia ; extra == 'all'
Requires-Dist: yacs ; extra == 'all'
Requires-Dist: brunette ; extra == 'all'
Requires-Dist: codecov ; extra == 'all'
Requires-Dist: coverage ; extra == 'all'
Requires-Dist: pytest ; extra == 'all'
Requires-Dist: pytest-cov ; extra == 'all'
Requires-Dist: pytest-subprocess ; extra == 'all'
Requires-Dist: xdoctest ; extra == 'all'
Provides-Extra: build
Requires-Dist: cmake ; extra == 'build'
Requires-Dist: ninja ; extra == 'build'
Requires-Dist: scikit-build ; extra == 'build'
Requires-Dist: setuptools ; extra == 'build'
Requires-Dist: setuptools-scm[toml] ; extra == 'build'
Requires-Dist: wheel ; extra == 'build'
Provides-Extra: runtime
Requires-Dist: efficientnet-pytorch ; extra == 'runtime'
Requires-Dist: matplotlib ; extra == 'runtime'
Requires-Dist: numpy ; extra == 'runtime'
Requires-Dist: scikit-image ; extra == 'runtime'
Requires-Dist: tensorboardX ; extra == 'runtime'
Requires-Dist: torch ; extra == 'runtime'
Requires-Dist: torchvision ; extra == 'runtime'
Requires-Dist: tqdm ; extra == 'runtime'
Requires-Dist: wbia-utool ; extra == 'runtime'
Requires-Dist: wildbook-ia ; extra == 'runtime'
Requires-Dist: yacs ; extra == 'runtime'
Provides-Extra: tests
Requires-Dist: brunette ; extra == 'tests'
Requires-Dist: codecov ; extra == 'tests'
Requires-Dist: coverage ; extra == 'tests'
Requires-Dist: pytest ; extra == 'tests'
Requires-Dist: pytest-cov ; extra == 'tests'
Requires-Dist: pytest-subprocess ; extra == 'tests'
Requires-Dist: xdoctest ; extra == 'tests'
